minecraft_text_components/__init__.py
minecraft_text_components/advances/__init__.py
minecraft_text_components/advances/get_advance.py
minecraft_text_components/advances/get_char_advance.py
minecraft_text_components/advances/get_line_advance.py
minecraft_text_components/alignment.py
minecraft_text_components/columns.py
minecraft_text_components/container.py
minecraft_text_components/contrib/__init__.py
minecraft_text_components/contrib/beet_minify.py
minecraft_text_components/flat.py
minecraft_text_components/formatting.py
minecraft_text_components/helpers.py
minecraft_text_components/join.py
minecraft_text_components/minify/__init__.py
minecraft_text_components/minify/factor_common_formatting.py
minecraft_text_components/minify/merged.py
minecraft_text_components/minify/minify.py
minecraft_text_components/minify/reduce.py
minecraft_text_components/overlap.py
minecraft_text_components/pad_each_line.py
minecraft_text_components/prevent_inheritance.py
minecraft_text_components/py.typed
minecraft_text_components/regex.py
minecraft_text_components/resources/advances.json
minecraft_text_components/resources/legacy_unicode_advances.json
minecraft_text_components/split.py
minecraft_text_components/style.py
minecraft_text_components/trim.py
minecraft_text_components/types.py
minecraft_text_components/whitespace.py
minecraft_text_components/wrap.py
minecraft_text_components-3.3.0.dist-info/LICENSE
minecraft_text_components-3.3.0.dist-info/METADATA
minecraft_text_components-3.3.0.dist-info/WHEEL
minecraft_text_components-3.3.0.dist-info/RECORD
