Metadata-Version: 2.1
Name: minecraft-text-components
Version: 3.3.0
Summary: A library for manipulating Minecraft's raw JSON text components
Home-page: https://github.com/VanillaTweaks/minecraft-text-components
License: MIT
Keywords: minecraft,pack,data,datapack,resource,resourcepack,raw,json,text,components
Author: VanillaTweaks
Author-email: team@vanillatweaks.net
Requires-Python: >=3.10,<4.0
Classifier: License :: OSI Approved :: MIT License
Classifier: Programming Language :: Python :: 3
Classifier: Programming Language :: Python :: 3.10
Classifier: Programming Language :: Python :: 3.11
Classifier: Programming Language :: Python :: 3.12
Provides-Extra: beet
Requires-Dist: beet (>=0.80.1,<1) ; extra == "beet"
Requires-Dist: mecha (>=0.61.0,<1) ; extra == "beet"
Requires-Dist: typing-extensions (>=4.4.0,<5.0.0)
Project-URL: Documentation, https://github.com/VanillaTweaks/minecraft-text-components
Project-URL: Repository, https://github.com/VanillaTweaks/minecraft-text-components
